ctg/__init__.py
ctg/_min_dependencies.py
ctg/_version.py
ctg/evaluation_main.py
ctg/instructions.py
ctg/instructions_registry.py
ctg/instructions_util.py
ctg/new_ctg.py
ctg/old_ctg.py
ctg/perplexity.py
ctg/wildguard_ctg.py
experiments/__init__.py
experiments/analysis.py
experiments/automatic_evaluation_1_llamaguard.py
experiments/automatic_evaluation_2_wildguard.py
experiments/generate_evaluation_responses.py
experiments/results_hidden_states.py
experiments/results_hidden_states_truncated.py
experiments/results_ifeval_performance.py
experiments/results_sbert.py
safenudge-0.1.0.dist-info/licenses/LICENSE
safenudge-0.1.0.dist-info/METADATA
safenudge-0.1.0.dist-info/WHEEL
safenudge-0.1.0.dist-info/top_level.txt
safenudge-0.1.0.dist-info/RECORD
