Metadata-Version: 2.4
Name: safenudge
Version: 0.1.0
Summary: A Python library with the implementation for the algorithms used in 'Safeguarding large language models in real-time with tunable safety-performance trade-offs', by J. Fonseca, A. Bell and J. Stoyanovich.
Home-page: https://github.com/joaopfonseca/safenudge
Download-URL: https://github.com/joaopfonseca/safenudge
Maintainer: J. Fonseca
Maintainer-email: jpm9748@nyu.edu
License: MIT
Classifier: Intended Audience :: Science/Research
Classifier: Intended Audience :: Developers
Classifier: License :: OSI Approved
Classifier: Programming Language :: Python
Classifier: Topic :: Software Development
Classifier: Topic :: Scientific/Engineering
Classifier: Operating System :: Microsoft :: Windows
Classifier: Operating System :: POSIX
Classifier: Operating System :: Unix
Classifier: Operating System :: MacOS
Classifier: Programming Language :: Python :: 3.10
Classifier: Programming Language :: Python :: 3.11
Classifier: Programming Language :: Python :: 3.12
Classifier: Programming Language :: Python :: 3.13
License-File: LICENSE
Requires-Dist: sentence-transformers>=3.3.1
Requires-Dist: transformers>=4.46.3
Requires-Dist: torch>=2.5.1
Requires-Dist: tqdm>=4.67.0
Requires-Dist: pandas>=2.2.3
Requires-Dist: numpy>=2.0.2
Requires-Dist: matplotlib>=3.9.2
Requires-Dist: scikit-learn>=1.5.2
Provides-Extra: optional
Provides-Extra: docs
Provides-Extra: examples
Provides-Extra: tests
Provides-Extra: all
Requires-Dist: sentence-transformers>=3.3.1; extra == "all"
Requires-Dist: transformers>=4.46.3; extra == "all"
Requires-Dist: torch>=2.5.1; extra == "all"
Requires-Dist: tqdm>=4.67.0; extra == "all"
Requires-Dist: pandas>=2.2.3; extra == "all"
Requires-Dist: numpy>=2.0.2; extra == "all"
Requires-Dist: matplotlib>=3.9.2; extra == "all"
Requires-Dist: scikit-learn>=1.5.2; extra == "all"
Dynamic: classifier
Dynamic: description
Dynamic: description-content-type
Dynamic: download-url
Dynamic: home-page
Dynamic: license
Dynamic: license-file
Dynamic: maintainer
Dynamic: maintainer-email
Dynamic: provides-extra
Dynamic: requires-dist
Dynamic: summary
